luckydep/__init__.py
luckydep/py.typed
luckydep-0.2.0.dist-info/METADATA
luckydep-0.2.0.dist-info/WHEEL
luckydep-0.2.0.dist-info/RECORD
