Metadata-Version: 2.4
Name: luckydep
Version: 0.2.0
Summary: Minimal dependency injection framework
Project-URL: Homepage, https://github.com/wdhongtw/luckydep
Author-email: Weida Hong <wdhongtw@gmail.com>
Classifier: License :: OSI Approved :: MIT License
Classifier: Operating System :: OS Independent
Classifier: Programming Language :: Python :: 3
Classifier: Topic :: Utilities
Classifier: Typing :: Typed
Requires-Python: >=3.7
